tesseractpro/__init__.py
tesseractpro/alerts.py
tesseractpro/base.py
tesseractpro/chart.py
tesseractpro/errors.py
tesseractpro/handle.py
tesseractpro/markets.py
tesseractpro/restclient.py
tesseractpro/timewindow.py
tesseractpro/tools/__init__.py
tesseractpro/tools/all_tools.py
tesseractpro/tools/angleline.py
tesseractpro/tools/arrow.py
tesseractpro/tools/basetool.py
tesseractpro/tools/circle.py
tesseractpro/tools/curve.py
tesseractpro/tools/fib_retracement.py
tesseractpro/tools/gann_box.py
tesseractpro/tools/gann_grid.py
tesseractpro/tools/gann_square.py
tesseractpro/tools/gannfan.py
tesseractpro/tools/horizontal_ray.py
tesseractpro/tools/image.py
tesseractpro/tools/line.py
tesseractpro/tools/magbox.py
tesseractpro/tools/marker.py
tesseractpro/tools/pitchfork.py
tesseractpro/tools/protractor.py
tesseractpro/tools/spiral.py
tesseractpro/tools/text.py
tesseractpro/tools/turningpoint.py
tesseractpro/tools/vertical_ray.py
tesseractpro/utils/__init__.py
tesseractpro/utils/event_emitter.py
tesseractpro/utils/socketio_utils.py
tesseractpro-0.1.4.dist-info/licenses/LICENSE
tesseractpro-0.1.4.dist-info/METADATA
tesseractpro-0.1.4.dist-info/WHEEL
tesseractpro-0.1.4.dist-info/top_level.txt
tesseractpro-0.1.4.dist-info/RECORD
