Metadata-Version: 2.4
Name: tesseractpro
Version: 0.1.4
Summary: The Tesseract Pro Python API
Home-page: https://github.com/tesseractpro/python-api
Author: Emiel van Goor
Author-email: info@tesseractpro.io
License: MIT
Keywords: TesseractPro API
Classifier: Intended Audience :: Developers
Classifier: Programming Language :: Python :: 3.9
Classifier: Programming Language :: Python :: 3.10
Classifier: Programming Language :: Python :: 3.11
Classifier: Operating System :: OS Independent
Requires-Python: >=3.9
License-File: LICENSE
Requires-Dist: python-socketio[client]>=5.0.0
Dynamic: author
Dynamic: author-email
Dynamic: classifier
Dynamic: description
Dynamic: description-content-type
Dynamic: home-page
Dynamic: keywords
Dynamic: license
Dynamic: license-file
Dynamic: requires-dist
Dynamic: requires-python
Dynamic: summary
